[
    {
        
        "image":"https://cdn.noitatnemucod.net/thumbnail/300x400/100/37eb9509a2ae0010f64b0170a03b5a13.jpg",
        "movieTitle":"Weathering with you",
        "moviedescription":"Tokyo is currently experiencing rain showers that seem to disrupt the usual pace of everyone living there to no end.",
        "moviemeta":"movie"
    },
    {
       
        "image": "https://cdn.noitatnemucod.net/thumbnail/300x400/100/a9b19137629f50c8bf9cb40353ecd52b.jpg",
        "movieTitle": "Maquia:when the Promised Flower",
        "moviedescription": "Tokyo is currently experiencing rain showers that seem to disrupt the usual pace of everyone living there to no end.",
        "moviemeta": "movie"
    },
    {
      
        "image": "https://cdn.noitatnemucod.net/thumbnail/300x400/100/9d5b6cad13eb8756a3e16ef40626c5a1.jpg",
        "movieTitle": "Grave of fireFlies",
        "moviedescription": "Tokyo is currently experiencing rain showers that seem to disrupt the usual pace of everyone living there to no end.",
        "moviemeta": "movie"
    },
    {
     
        "image": "https://cdn.noitatnemucod.net/thumbnail/300x400/100/1c947d2c7a7728257c2bb1c4ef1417d9.jpg",
        "movieTitle": "Steins,Gate:The Movie-Load",
        "moviedescription": "Tokyo is currently experiencing rain showers that seem to disrupt the usual pace of everyone living there to no end.",
        "moviemeta": "movie"
    },
    {
    
        "image": "https://cdn.noitatnemucod.net/thumbnail/300x400/100/1d226c74f7248dda6aac32d8f915b8f1.jpg",
        "movieTitle": "Spirited Away",
        "moviedescription": "Tokyo is currently experiencing rain showers that seem to disrupt the usual pace of everyone living there to no end.",
        "moviemeta": "movie"
    },
    {
    
        "image": "https://cdn.noitatnemucod.net/thumbnail/300x400/100/16eec56baf8f3fcc6430607f58ce3d12.jpg",
        "movieTitle": "Your Name",
        "moviedescription": "Tokyo is currently experiencing rain showers that seem to disrupt the usual pace of everyone living there to no end.",
        "moviemeta": "movie"
    },
    {
     
        "image": "https://cdn.noitatnemucod.net/thumbnail/300x400/100/7fc61d82b89949dff4319bd73ff2d456.jpg",
        "movieTitle": "A slient Voice",
        "moviedescription": "Tokyo is currently experiencing rain showers that seem to disrupt the usual pace of everyone living there to no end.",
        "moviemeta": "movie"
    },
    {
        "image": "https://cdn.noitatnemucod.net/thumbnail/300x400/100/98f207050b0ff96bd5a558890e1f0672.jpg",
        "movieTitle": "Fale/Stay night",
        "moviedescription": "Tokyo is currently experiencing rain showers that seem to disrupt the usual pace of everyone living there to no end.",
        "moviemeta": "movie"
    },
    {
    
        "image": "https://cdn.noitatnemucod.net/thumbnail/300x400/100/12d035088d46d18d76f751d07ef8e31e.jpg",
        "movieTitle": "Princess Mononoke",
        "moviedescription": "Tokyo is currently experiencing rain showers that seem to disrupt the usual pace of everyone living there to no end.",
        "moviemeta": "movie"
    },
    {
     
        "image": "https://cdn.noitatnemucod.net/thumbnail/300x400/100/12d035088d46d18d76f751d07ef8e31e.jpg",
        "movieTitle": "Wolf Children",
        "moviedescription": "Tokyo is currently experiencing rain showers that seem to disrupt the usual pace of everyone living there to no end.",
        "moviemeta": "movie"
    },
    {
        "image":"https://cdn.noitatnemucod.net/thumbnail/300x400/100/890b72a89c29f9f02ffe82bdbf1f8298.jpg",
        "movieTitle":"You And Idol Precure",
        "moviedescription":"HiAnime is the best site to watch You and Idol Precure♪ ",
        "moviemeta":"TvShow"
    },
    {
        "image": "https://cdn.noitatnemucod.net/thumbnail/300x400/100/1029517b0a555432b4aacbec862ad2a0.jpg",
        "movieTitle": "Blue Exorcist:The Blue Night Saga",
        "moviedescription": "HiAnime is the best site to watch You and Idol Precure♪ ",
        "moviemeta": "TvShow"
    },
    {
        "image": "https://cdn.noitatnemucod.net/thumbnail/300x400/100/aa2cb028fd55a639ceccab8c94fbd4b4.jpg",
        "movieTitle": "Beheneko:The Elf-Girls",
        "moviedescription": "HiAnime is the best site to watch You and Idol Precure♪ ",
        "moviemeta": "TvShow"
    },
    {
        "image": "https://cdn.noitatnemucod.net/thumbnail/300x400/100/b5299e74c03c66b207ade517e9f982d9.jpg",
        "movieTitle": "Jochum",
        "moviedescription": "HiAnime is the best site to watch You and Idol Precure♪ ",
        "moviemeta": "TvShow"
    },
    {
        "image": "https://cdn.noitatnemucod.net/thumbnail/300x400/100/506aea20fdcd12c83bfc8bd5969099e1.jpg",
        "movieTitle": "Mashin Souzounden",
        "moviedescription": "HiAnime is the best site to watch You and Idol Precure♪ ",
        "moviemeta": "TvShow"
    },
    {
        "image": "https://cdn.noitatnemucod.net/thumbnail/300x400/100/d154104a2f93c0a20bd73247e08f3e8d.jpg",
        "movieTitle": "Card Fight",
        "moviedescription": "HiAnime is the best site to watch You and Idol Precure♪ ",
        "moviemeta": "TvShow"
    },
    {
        "image": "https://cdn.noitatnemucod.net/thumbnail/300x400/100/3456bcff1c43aa7b8e291e1df25f7e36.jpg",
        "movieTitle": "0 Year old Child",
        "moviedescription": "HiAnime is the best site to watch You and Idol Precure♪ ",
        "moviemeta": "TvShow"
    },
    {
        "image": "https://cdn.noitatnemucod.net/thumbnail/300x400/100/a1b3a3a817812790340792ef2c304907.jpg",
        "movieTitle": "Yami Shibai 14",
        "moviedescription": "HiAnime is the best site to watch You and Idol Precure♪ ",
        "moviemeta": "TvShow"
    },
    {
        "image": "https://cdn.noitatnemucod.net/thumbnail/300x400/100/3a7b5cba2d67765cd68ecb320a11c633.jpg",
        "movieTitle": "The Daily Life of....",
        "moviedescription": "HiAnime is the best site to watch You and Idol Precure♪ ",
        "moviemeta": "TvShow"
    },
    {
        "image": "https://cdn.noitatnemucod.net/thumbnail/300x400/100/a6300540f34ce2a0244b9210b98788af.jpg",
        "movieTitle": "Headhuted To Another",
        "moviedescription": "HiAnime is the best site to watch You and Idol Precure♪ ",
        "moviemeta": "TvShow"
    },
    {
        "image": "https://cdn.noitatnemucod.net/thumbnail/300x400/100/bcd84731a3eda4f4a306250769675065.jpg",
        "movieTitle": "OnePiece",
        "moviedescription": " strongest and most infamous being to have sailed the Grand Line.",
        "moviemeta": "MostPopular"
    },
    {
        "image": "https://cdn.noitatnemucod.net/thumbnail/300x400/100/9cbcf87f54194742e7686119089478f8.jpg",
        "movieTitle": "Naruto:Shippoden",
        "moviedescription": " strongest and most infamous being to have sailed the Grand Line.",
        "moviemeta": "MostPopular"
    },
    {
        "image": "https://cdn.noitatnemucod.net/thumbnail/300x400/100/bd5ae1d387a59c5abcf5e1a6a616728c.jpg",
        "movieTitle": "Bleach",
        "moviedescription": " strongest and most infamous being to have sailed the Grand Line.",
        "moviemeta": "MostPopular"
    },
    {
        "image": "https://cdn.noitatnemucod.net/thumbnail/300x400/100/b51f863b05f30576cf9d85fa9b911bb5.png",
        "movieTitle": "Jujusu Kasion",
        "moviedescription": " strongest and most infamous being to have sailed the Grand Line.",
        "moviemeta": "MostPopular"
    },
    {
        "image": "https://cdn.noitatnemucod.net/thumbnail/300x400/100/db2f3ce7b9cab7fdc160b005bffb899a.png",
        "movieTitle": "Demon Slayer",
        "moviedescription": " strongest and most infamous being to have sailed the Grand Line.",
        "moviemeta": "MostPopular"
    },
    {
        "image": "https://cdn.noitatnemucod.net/thumbnail/300x400/100/65f92e6e315a931ef872da4b312442b8.jpg",
        "movieTitle": "Solo Leveling",
        "moviedescription": " strongest and most infamous being to have sailed the Grand Line.",
        "moviemeta": "MostPopular"
    },
    {
        "image": "https://cdn.noitatnemucod.net/thumbnail/300x400/100/88bd17534dc4884f23027035d23d74e5.jpg",
        "movieTitle": "Spyxfamily",
        "moviedescription": " strongest and most infamous being to have sailed the Grand Line.",
        "moviemeta": "MostPopular"
    },
    {
        "image": "https://cdn.noitatnemucod.net/thumbnail/300x400/100/993c0361975cce4c7fbb11f8558f9664.jpg",
        "movieTitle": "Hunterx Hunter",
        "moviedescription": " strongest and most infamous being to have sailed the Grand Line.",
        "moviemeta": "MostPopular"
    },
    {
        "image": "https://cdn.noitatnemucod.net/thumbnail/300x400/100/fced51e392ffd80041b3a1581ba7de2f.jpg",
        "movieTitle": "Blue Lock",
        "moviedescription": " strongest and most infamous being to have sailed the Grand Line.",
        "moviemeta": "MostPopular"
    },
    {
        "image": "https://cdn.noitatnemucod.net/thumbnail/300x400/100/bcd84731a3eda4f4a306250769675065.jpg",
        "movieTitle": "OnePiece",
        "moviedescription": "HiAnime is the best site to watch Solo Leveling",
        "moviemeta": "TopAiring"
    },
    {
        "image": "https://cdn.noitatnemucod.net/thumbnail/300x400/100/0fc66f9879a3a4a15408c325e1677e17.jpg",
        "movieTitle": "Shangri-la",
        "moviedescription": "HiAnime is the best site to watch Solo Leveling",
        "moviemeta": "TopAiring"
    },
    {
        "image": "https://cdn.noitatnemucod.net/thumbnail/300x400/100/2bbe7ece956bbefc6f385a7a447c182c.jpg",
        "movieTitle": "Sakamoto days",
        "moviedescription": "HiAnime is the best site to watch Solo Leveling",
        "moviemeta": "TopAiring"
    },
    {
        "image": "https://cdn.noitatnemucod.net/thumbnail/300x400/100/fc1904280b9effa1624c0d2b2652aa52.jpg",
        "movieTitle": "Super drayen",
        "moviedescription": "HiAnime is the best site to watch Solo Leveling",
        "moviemeta": "TopAiring"
    },
    {
        "image": "https://cdn.noitatnemucod.net/thumbnail/300x400/100/e91ce663a30bda517c5a191c575a16c0.jpg",
        "movieTitle": "The 100 girl friends",
        "moviedescription": "HiAnime is the best site to watch Solo Leveling",
        "moviemeta": "TopAiring"
    },
    {
        "image": "https://cdn.noitatnemucod.net/thumbnail/300x400/100/aa3d2d4f726cbea8854acd327c9cec94.jpg",
        "movieTitle": "Ubel Blat",
        "moviedescription": "HiAnime is the best site to watch Solo Leveling",
        "moviemeta": "TopAiring"
    },
    {
        "image": "https://cdn.noitatnemucod.net/thumbnail/300x400/100/231f4704ef8573817aea6df75e25a3a4.jpg",
        "movieTitle": "Can you keep a secret",
        "moviedescription": "HiAnime is the best site to watch Solo Leveling",
        "moviemeta": "TopAiring"
    },
    {
        "image": "https://cdn.noitatnemucod.net/thumbnail/300x400/100/048335c20023c4339a39c30686f07841.jpg",
        "movieTitle": "from Bureaucralto",
        "moviedescription": "HiAnime is the best site to watch Solo Leveling",
        "moviemeta": "TopAiring"
    },
    {
        "image": "https://cdn.noitatnemucod.net/thumbnail/300x400/100/5b3019270b9e06f5cb0f8a788d1b2d1a.jpg",
        "movieTitle": "Zenshu",
        "moviedescription": "HiAnime is the best site to watch Solo Leveling",
        "moviemeta": "TopAiring"
    },
    {
        "image": "https://cdn.noitatnemucod.net/thumbnail/300x400/100/ac8389e16478cd7283b8769c7ec9b484.jpg",
        "movieTitle": "I may bea guild",
        "moviedescription": "HiAnime is the best site to watch Solo Leveling",
        "moviemeta": "TopAiring"
    }  

]